djpg/__init__.py
djpg/codes.py
djpg/exceptions.py
djpg/models.py
djpg/signals.py
djpg/urls.py
djpg/views.py
djpg-0.2.0.dist-info/METADATA
djpg-0.2.0.dist-info/RECORD
djpg-0.2.0.dist-info/WHEEL
djpg-0.2.0.dist-info/top_level.txt
