Metadata-Version: 2.1
Name: djpg
Version: 0.2.0
Summary: djpg is a Django module that integrates with the online payment service PagSeguro.
Home-page: https://github.com/mstrcnvs/djpg
Author: Rafael Canovas
Author-email: rafaelcanovas@me.com
License: The MIT License (MIT)
Requires-Dist: requests (==2.18.4)
Requires-Dist: xmltodict (==0.11.0)
